{
  "phoneCodes": [
    {
      "name": "South Georgia",
      "code": "+500"
    },
    {
      "name": "Grenada",
      "code": "+1473"
    },
    {
      "name": "Switzerland",
      "code": "+41"
    },
    {
      "name": "Sierra Leone",
      "code": "+232"
    },
    {
      "name": "Hungary",
      "code": "+36"
    },
    {
      "name": "Taiwan",
      "code": "+886"
    },
    {
      "name": "Wallis and Futuna",
      "code": "+681"
    },
    {
      "name": "Barbados",
      "code": "+1246"
    },
    {
      "name": "Pitcairn Islands",
      "code": "+64"
    },
    {
      "name": "Ivory Coast",
      "code": "+225"
    },
    {
      "name": "Tunisia",
      "code": "+216"
    },
    {
      "name": "Italy",
      "code": "+39"
    },
    {
      "name": "Benin",
      "code": "+229"
    },
    {
      "name": "Indonesia",
      "code": "+62"
    },
    {
      "name": "Cape Verde",
      "code": "+238"
    },
    {
      "name": "Saint Kitts and Nevis",
      "code": "+1869"
    },
    {
      "name": "Laos",
      "code": "+856"
    },
    {
      "name": "Caribbean Netherlands",
      "code": "+599"
    },
    {
      "name": "Uganda",
      "code": "+256"
    },
    {
      "name": "Andorra",
      "code": "+376"
    },
    {
      "name": "Burundi",
      "code": "+257"
    },
    {
      "name": "South Africa",
      "code": "+27"
    },
    {
      "name": "France",
      "code": "+33"
    },
    {
      "name": "Libya",
      "code": "+218"
    },
    {
      "name": "Mexico",
      "code": "+52"
    },
    {
      "name": "Gabon",
      "code": "+241"
    },
    {
      "name": "Northern Mariana Islands",
      "code": "+1670"
    },
    {
      "name": "North Macedonia",
      "code": "+389"
    },
    {
      "name": "China",
      "code": "+86"
    },
    {
      "name": "Yemen",
      "code": "+967"
    },
    {
      "name": "Saint Barth\u00e9lemy",
      "code": "+590"
    },
    {
      "name": "Guernsey",
      "code": "+44"
    },
    {
      "name": "Solomon Islands",
      "code": "+677"
    },
    {
      "name": "Svalbard and Jan Mayen",
      "code": "+4779"
    },
    {
      "name": "Faroe Islands",
      "code": "+298"
    },
    {
      "name": "Uzbekistan",
      "code": "+998"
    },
    {
      "name": "Egypt",
      "code": "+20"
    },
    {
      "name": "Senegal",
      "code": "+221"
    },
    {
      "name": "Sri Lanka",
      "code": "+94"
    },
    {
      "name": "Palestine",
      "code": "+970"
    },
    {
      "name": "Bangladesh",
      "code": "+880"
    },
    {
      "name": "Peru",
      "code": "+51"
    },
    {
      "name": "Singapore",
      "code": "+65"
    },
    {
      "name": "Turkey",
      "code": "+90"
    },
    {
      "name": "Afghanistan",
      "code": "+93"
    },
    {
      "name": "Aruba",
      "code": "+297"
    },
    {
      "name": "Cook Islands",
      "code": "+682"
    },
    {
      "name": "United Kingdom",
      "code": "+44"
    },
    {
      "name": "Zambia",
      "code": "+260"
    },
    {
      "name": "Finland",
      "code": "+358"
    },
    {
      "name": "Niger",
      "code": "+227"
    },
    {
      "name": "Christmas Island",
      "code": "+61"
    },
    {
      "name": "Tokelau",
      "code": "+690"
    },
    {
      "name": "Guinea-Bissau",
      "code": "+245"
    },
    {
      "name": "Azerbaijan",
      "code": "+994"
    },
    {
      "name": "R\u00e9union",
      "code": "+262"
    },
    {
      "name": "Djibouti",
      "code": "+253"
    },
    {
      "name": "North Korea",
      "code": "+850"
    },
    {
      "name": "Mauritius",
      "code": "+230"
    },
    {
      "name": "Montserrat",
      "code": "+1664"
    },
    {
      "name": "United States Virgin Islands",
      "code": "+1340"
    },
    {
      "name": "Colombia",
      "code": "+57"
    },
    {
      "name": "Greece",
      "code": "+30"
    },
    {
      "name": "Croatia",
      "code": "+385"
    },
    {
      "name": "Morocco",
      "code": "+212"
    },
    {
      "name": "Algeria",
      "code": "+213"
    },
    {
      "name": "Netherlands",
      "code": "+31"
    },
    {
      "name": "Sudan",
      "code": "+249"
    },
    {
      "name": "Fiji",
      "code": "+679"
    },
    {
      "name": "Liechtenstein",
      "code": "+423"
    },
    {
      "name": "Nepal",
      "code": "+977"
    },
    {
      "name": "Puerto Rico",
      "code": "+1787939"
    },
    {
      "name": "Georgia",
      "code": "+995"
    },
    {
      "name": "Pakistan",
      "code": "+92"
    },
    {
      "name": "Monaco",
      "code": "+377"
    },
    {
      "name": "Botswana",
      "code": "+267"
    },
    {
      "name": "Lebanon",
      "code": "+961"
    },
    {
      "name": "Papua New Guinea",
      "code": "+675"
    },
    {
      "name": "Mayotte",
      "code": "+262"
    },
    {
      "name": "Dominican Republic",
      "code": "+1809829849"
    },
    {
      "name": "Norfolk Island",
      "code": "+672"
    },
    {
      "name": "Bouvet Island",
      "code": "+47"
    },
    {
      "name": "Qatar",
      "code": "+974"
    },
    {
      "name": "Madagascar",
      "code": "+261"
    },
    {
      "name": "India",
      "code": "+91"
    },
    {
      "name": "Syria",
      "code": "+963"
    },
    {
      "name": "Montenegro",
      "code": "+382"
    },
    {
      "name": "Eswatini",
      "code": "+268"
    },
    {
      "name": "Paraguay",
      "code": "+595"
    },
    {
      "name": "El Salvador",
      "code": "+503"
    },
    {
      "name": "Ukraine",
      "code": "+380"
    },
    {
      "name": "Isle of Man",
      "code": "+44"
    },
    {
      "name": "Namibia",
      "code": "+264"
    },
    {
      "name": "United Arab Emirates",
      "code": "+971"
    },
    {
      "name": "Bulgaria",
      "code": "+359"
    },
    {
      "name": "Greenland",
      "code": "+299"
    },
    {
      "name": "Germany",
      "code": "+49"
    },
    {
      "name": "Cambodia",
      "code": "+855"
    },
    {
      "name": "Iraq",
      "code": "+964"
    },
    {
      "name": "French Southern and Antarctic Lands",
      "code": "+262"
    },
    {
      "name": "Sweden",
      "code": "+46"
    },
    {
      "name": "Cuba",
      "code": "+53"
    },
    {
      "name": "Kyrgyzstan",
      "code": "+996"
    },
    {
      "name": "Russia",
      "code": "+734589"
    },
    {
      "name": "Malaysia",
      "code": "+60"
    },
    {
      "name": "S\u00e3o Tom\u00e9 and Pr\u00edncipe",
      "code": "+239"
    },
    {
      "name": "Cyprus",
      "code": "+357"
    },
    {
      "name": "Canada",
      "code": "+1"
    },
    {
      "name": "Malawi",
      "code": "+265"
    },
    {
      "name": "Saudi Arabia",
      "code": "+966"
    },
    {
      "name": "Bosnia and Herzegovina",
      "code": "+387"
    },
    {
      "name": "Ethiopia",
      "code": "+251"
    },
    {
      "name": "Spain",
      "code": "+34"
    },
    {
      "name": "Slovenia",
      "code": "+386"
    },
    {
      "name": "Oman",
      "code": "+968"
    },
    {
      "name": "Saint Pierre and Miquelon",
      "code": "+508"
    },
    {
      "name": "Macau",
      "code": "+853"
    },
    {
      "name": "San Marino",
      "code": "+378"
    },
    {
      "name": "Lesotho",
      "code": "+266"
    },
    {
      "name": "Marshall Islands",
      "code": "+692"
    },
    {
      "name": "Sint Maarten",
      "code": "+1721"
    },
    {
      "name": "Iceland",
      "code": "+354"
    },
    {
      "name": "Luxembourg",
      "code": "+352"
    },
    {
      "name": "Argentina",
      "code": "+54"
    },
    {
      "name": "Turks and Caicos Islands",
      "code": "+1649"
    },
    {
      "name": "Nauru",
      "code": "+674"
    },
    {
      "name": "Cocos (Keeling) Islands",
      "code": "+61"
    },
    {
      "name": "Western Sahara",
      "code": "+2125288125289"
    },
    {
      "name": "Dominica",
      "code": "+1767"
    },
    {
      "name": "Costa Rica",
      "code": "+506"
    },
    {
      "name": "Australia",
      "code": "+61"
    },
    {
      "name": "Thailand",
      "code": "+66"
    },
    {
      "name": "Haiti",
      "code": "+509"
    },
    {
      "name": "Tuvalu",
      "code": "+688"
    },
    {
      "name": "Honduras",
      "code": "+504"
    },
    {
      "name": "Equatorial Guinea",
      "code": "+240"
    },
    {
      "name": "Saint Lucia",
      "code": "+1758"
    },
    {
      "name": "French Polynesia",
      "code": "+689"
    },
    {
      "name": "Belarus",
      "code": "+375"
    },
    {
      "name": "Latvia",
      "code": "+371"
    },
    {
      "name": "Palau",
      "code": "+680"
    },
    {
      "name": "Guadeloupe",
      "code": "+590"
    },
    {
      "name": "Philippines",
      "code": "+63"
    },
    {
      "name": "Gibraltar",
      "code": "+350"
    },
    {
      "name": "Denmark",
      "code": "+45"
    },
    {
      "name": "Cameroon",
      "code": "+237"
    },
    {
      "name": "Guinea",
      "code": "+224"
    },
    {
      "name": "Bahrain",
      "code": "+973"
    },
    {
      "name": "Suriname",
      "code": "+597"
    },
    {
      "name": "DR Congo",
      "code": "+243"
    },
    {
      "name": "Somalia",
      "code": "+252"
    },
    {
      "name": "Czechia",
      "code": "+420"
    },
    {
      "name": "New Caledonia",
      "code": "+687"
    },
    {
      "name": "Vanuatu",
      "code": "+678"
    },
    {
      "name": "Saint Helena, Ascension and Tristan da Cunha",
      "code": "+29047"
    },
    {
      "name": "Togo",
      "code": "+228"
    },
    {
      "name": "British Virgin Islands",
      "code": "+1284"
    },
    {
      "name": "Kenya",
      "code": "+254"
    },
    {
      "name": "Niue",
      "code": "+683"
    },
    {
      "name": "Rwanda",
      "code": "+250"
    },
    {
      "name": "Estonia",
      "code": "+372"
    },
    {
      "name": "Romania",
      "code": "+40"
    },
    {
      "name": "Trinidad and Tobago",
      "code": "+1868"
    },
    {
      "name": "Guyana",
      "code": "+592"
    },
    {
      "name": "Timor-Leste",
      "code": "+670"
    },
    {
      "name": "Vietnam",
      "code": "+84"
    },
    {
      "name": "Uruguay",
      "code": "+598"
    },
    {
      "name": "Vatican City",
      "code": "+390669879"
    },
    {
      "name": "Hong Kong",
      "code": "+852"
    },
    {
      "name": "Austria",
      "code": "+43"
    },
    {
      "name": "Antigua and Barbuda",
      "code": "+1268"
    },
    {
      "name": "Turkmenistan",
      "code": "+993"
    },
    {
      "name": "Mozambique",
      "code": "+258"
    },
    {
      "name": "Panama",
      "code": "+507"
    },
    {
      "name": "Micronesia",
      "code": "+691"
    },
    {
      "name": "Ireland",
      "code": "+353"
    },
    {
      "name": "Cura\u00e7ao",
      "code": "+599"
    },
    {
      "name": "French Guiana",
      "code": "+594"
    },
    {
      "name": "Norway",
      "code": "+47"
    },
    {
      "name": "\u00c5land Islands",
      "code": "+35818"
    },
    {
      "name": "Central African Republic",
      "code": "+236"
    },
    {
      "name": "Burkina Faso",
      "code": "+226"
    },
    {
      "name": "Eritrea",
      "code": "+291"
    },
    {
      "name": "Tanzania",
      "code": "+255"
    },
    {
      "name": "South Korea",
      "code": "+82"
    },
    {
      "name": "Jordan",
      "code": "+962"
    },
    {
      "name": "Mauritania",
      "code": "+222"
    },
    {
      "name": "Lithuania",
      "code": "+370"
    },
    {
      "name": "United States Minor Outlying Islands",
      "code": "+268"
    },
    {
      "name": "Slovakia",
      "code": "+421"
    },
    {
      "name": "Angola",
      "code": "+244"
    },
    {
      "name": "Kazakhstan",
      "code": "+767"
    },
    {
      "name": "Moldova",
      "code": "+373"
    },
    {
      "name": "Mali",
      "code": "+223"
    },
    {
      "name": "Falkland Islands",
      "code": "+500"
    },
    {
      "name": "Armenia",
      "code": "+374"
    },
    {
      "name": "Samoa",
      "code": "+685"
    },
    {
      "name": "Jersey",
      "code": "+44"
    },
    {
      "name": "Japan",
      "code": "+81"
    },
    {
      "name": "Bolivia",
      "code": "+591"
    },
    {
      "name": "Chile",
      "code": "+56"
    },
    {
      "name": "United States",
      "code": "+1"
    },
    {
      "name": "Saint Vincent and the Grenadines",
      "code": "+1784"
    },
    {
      "name": "Bermuda",
      "code": "+1441"
    },
    {
      "name": "Seychelles",
      "code": "+248"
    },
    {
      "name": "British Indian Ocean Territory",
      "code": "+246"
    },
    {
      "name": "Guatemala",
      "code": "+502"
    },
    {
      "name": "Ecuador",
      "code": "+593"
    },
    {
      "name": "Martinique",
      "code": "+596"
    },
    {
      "name": "Tajikistan",
      "code": "+992"
    },
    {
      "name": "Malta",
      "code": "+356"
    },
    {
      "name": "Gambia",
      "code": "+220"
    },
    {
      "name": "Nigeria",
      "code": "+234"
    },
    {
      "name": "Bahamas",
      "code": "+1242"
    },
    {
      "name": "Kosovo",
      "code": "+383"
    },
    {
      "name": "Kuwait",
      "code": "+965"
    },
    {
      "name": "Maldives",
      "code": "+960"
    },
    {
      "name": "South Sudan",
      "code": "+211"
    },
    {
      "name": "Iran",
      "code": "+98"
    },
    {
      "name": "Albania",
      "code": "+355"
    },
    {
      "name": "Brazil",
      "code": "+55"
    },
    {
      "name": "Serbia",
      "code": "+381"
    },
    {
      "name": "Belize",
      "code": "+501"
    },
    {
      "name": "Myanmar",
      "code": "+95"
    },
    {
      "name": "Bhutan",
      "code": "+975"
    },
    {
      "name": "Venezuela",
      "code": "+58"
    },
    {
      "name": "Liberia",
      "code": "+231"
    },
    {
      "name": "Jamaica",
      "code": "+1876"
    },
    {
      "name": "Poland",
      "code": "+48"
    },
    {
      "name": "Cayman Islands",
      "code": "+1345"
    },
    {
      "name": "Brunei",
      "code": "+673"
    },
    {
      "name": "Comoros",
      "code": "+269"
    },
    {
      "name": "Guam",
      "code": "+1671"
    },
    {
      "name": "Tonga",
      "code": "+676"
    },
    {
      "name": "Kiribati",
      "code": "+686"
    },
    {
      "name": "Ghana",
      "code": "+233"
    },
    {
      "name": "Chad",
      "code": "+235"
    },
    {
      "name": "Zimbabwe",
      "code": "+263"
    },
    {
      "name": "Saint Martin",
      "code": "+590"
    },
    {
      "name": "Mongolia",
      "code": "+976"
    },
    {
      "name": "Portugal",
      "code": "+351"
    },
    {
      "name": "American Samoa",
      "code": "+1684"
    },
    {
      "name": "Republic of the Congo",
      "code": "+242"
    },
    {
      "name": "Belgium",
      "code": "+32"
    },
    {
      "name": "Israel",
      "code": "+972"
    },
    {
      "name": "New Zealand",
      "code": "+64"
    },
    {
      "name": "Nicaragua",
      "code": "+505"
    },
    {
      "name": "Anguilla",
      "code": "+1264"
    }
  ]
}
